mcpreadiness/__init__.py
mcpreadiness/__main__.py
mcpreadiness/cli.py
mcpreadiness/config.py
mcpreadiness/core/__init__.py
mcpreadiness/core/diff.py
mcpreadiness/core/models.py
mcpreadiness/core/orchestrator.py
mcpreadiness/core/taxonomy.py
mcpreadiness/providers/__init__.py
mcpreadiness/providers/base.py
mcpreadiness/providers/heuristic_provider.py
mcpreadiness/providers/llm_judge_provider.py
mcpreadiness/providers/opa_provider.py
mcpreadiness/providers/yara_provider.py
mcpreadiness/reports/__init__.py
mcpreadiness/reports/diff_report.py
mcpreadiness/reports/html_report.py
mcpreadiness/reports/json_report.py
mcpreadiness/reports/markdown_report.py
mcpreadiness/reports/sarif.py
mcpreadiness/rules/operational/dangerous_phrases.yar
mcpreadiness/rules/operational/excessive_capabilities.yar
mcpreadiness/rules/operational/missing_observability.yar
mcpreadiness/rules/operational/missing_timeout_field.yar
mcpreadiness/rules/operational/non_deterministic_behavior.yar
mcpreadiness/rules/operational/resource_management.yar
mcpreadiness/rules/operational/unsafe_retry_loops.yar
mcpreadiness/rules/policies/error_schema_required.rego
mcpreadiness/rules/policies/max_capabilities.rego
mcpreadiness/rules/policies/timeout_required.rego
mcp_readiness_scanner-0.1.0.dist-info/METADATA
mcp_readiness_scanner-0.1.0.dist-info/WHEEL
mcp_readiness_scanner-0.1.0.dist-info/entry_points.txt
mcp_readiness_scanner-0.1.0.dist-info/licenses/LICENSE
mcp_readiness_scanner-0.1.0.dist-info/RECORD
