Metadata-Version: 2.4
Name: mcp-readiness-scanner
Version: 0.1.0
Summary: Production readiness scanner for MCP servers and agentic AI tools
Project-URL: Homepage, https://github.com/mcp-readiness/scanner
Project-URL: Documentation, https://github.com/mcp-readiness/scanner/tree/main/docs
Project-URL: Repository, https://github.com/mcp-readiness/scanner
Project-URL: Issues, https://github.com/mcp-readiness/scanner/issues
Author: MCP Readiness Scanner Contributors
License-Expression: Apache-2.0
License-File: LICENSE
Keywords: agentic-ai,linter,mcp,model-context-protocol,operational-readiness,production-readiness,static-analysis
Classifier: Development Status :: 4 - Beta
Classifier: Environment :: Console
Classifier: Intended Audience :: Developers
Classifier: License :: OSI Approved :: Apache Software License
Classifier: Operating System :: OS Independent
Classifier: Programming Language :: Python :: 3
Classifier: Programming Language :: Python :: 3.11
Classifier: Programming Language :: Python :: 3.12
Classifier: Programming Language :: Python :: 3.13
Classifier: Topic :: Software Development :: Quality Assurance
Classifier: Topic :: Software Development :: Testing
Classifier: Typing :: Typed
Requires-Python: >=3.11
Requires-Dist: click>=8.0.0
Requires-Dist: pydantic>=2.0.0
Provides-Extra: all
Requires-Dist: litellm>=1.0.0; extra == 'all'
Requires-Dist: pyyaml>=6.0; extra == 'all'
Requires-Dist: yara-python>=4.3.0; extra == 'all'
Provides-Extra: dev
Requires-Dist: mypy>=1.0.0; extra == 'dev'
Requires-Dist: pytest-asyncio>=0.21.0; extra == 'dev'
Requires-Dist: pytest-cov>=4.0.0; extra == 'dev'
Requires-Dist: pytest>=7.0.0; extra == 'dev'
Requires-Dist: ruff>=0.1.0; extra == 'dev'
Requires-Dist: tomli-w>=1.0.0; extra == 'dev'
Provides-Extra: llm
Requires-Dist: litellm>=1.0.0; extra == 'llm'
Provides-Extra: yaml
Requires-Dist: pyyaml>=6.0; extra == 'yaml'
Provides-Extra: yara
Requires-Dist: yara-python>=4.3.0; extra == 'yara'
